tispost/__init__.py
tispost/collection.py
tispost/server.py
tispost/session.py
tispost-0.1.0.dist-info/LICENSE
tispost-0.1.0.dist-info/METADATA
tispost-0.1.0.dist-info/WHEEL
tispost-0.1.0.dist-info/top_level.txt
tispost-0.1.0.dist-info/RECORD
