Metadata-Version: 2.1
Name: tispost
Version: 0.1.0
Summary: Lightweight library for using postgres as nosql database
Home-page: https://github.com/aiselis/tispost
Author: Alessio Pinna
Author-email: alessio.pinna@aiselis.com
Maintainer: Alessio Pinna <alessio.pinna@aiselis.com>
License: Apache 2
Project-URL: Bug Reports, https://github.com/aiselis/tispost/issues
Project-URL: Source, https://github.com/aiselis/tispost
Platform: UNKNOWN
Classifier: License :: OSI Approved :: Apache Software License
Classifier: Intended Audience :: Developers
Classifier: Programming Language :: Python
Classifier: Programming Language :: Python :: 3
Classifier: Programming Language :: Python :: 3.6
Classifier: Programming Language :: Python :: 3.7
Classifier: Programming Language :: Python :: 3.8
Classifier: Development Status :: 3 - Alpha
Classifier: Operating System :: POSIX
Classifier: Operating System :: MacOS :: MacOS X
Classifier: Operating System :: Microsoft :: Windows
Classifier: Framework :: AsyncIO
Requires-Python: >=3.6
Requires-Dist: aiopg
